admin/__init__.py
admin/v1/__init__.py
admin/v1/admin_pb2.py
admin/v1/admin_pb2_grpc.py
messaging/__init__.py
messaging/v1/__init__.py
messaging/v1/messaging_pb2.py
messaging/v1/messaging_pb2_grpc.py
neoncontract_gen-1.5.0.dist-info/METADATA
neoncontract_gen-1.5.0.dist-info/WHEEL
neoncontract_gen-1.5.0.dist-info/top_level.txt
neoncontract_gen-1.5.0.dist-info/RECORD
