Metadata-Version: 2.4
Name: neoncontract-gen
Version: 1.5.0
Summary: NeonContract Protocol Buffer definitions for Python - Generated SDK
Author-email: LetA-Tech <dev@leta.tech>
License: MIT
Project-URL: Homepage, https://github.com/LetA-Tech/mcfo-neoncontract
Project-URL: Repository, https://github.com/LetA-Tech/mcfo-neoncontract
Classifier: Development Status :: 5 - Production/Stable
Classifier: Intended Audience :: Developers
Classifier: License :: OSI Approved :: MIT License
Classifier: Programming Language :: Python :: 3
Classifier: Programming Language :: Python :: 3.8
Classifier: Programming Language :: Python :: 3.9
Classifier: Programming Language :: Python :: 3.10
Classifier: Programming Language :: Python :: 3.11
Classifier: Programming Language :: Python :: 3.12
Classifier: Topic :: Software Development :: Libraries :: Python Modules
Requires-Python: >=3.8
Requires-Dist: grpcio>=1.58.0
Requires-Dist: grpcio-tools>=1.58.0
Requires-Dist: protobuf>=4.24.0
Dynamic: requires-python
